paginator/__init__.py
let45fc_paginator-0.1.dist-info/LICENSE
let45fc_paginator-0.1.dist-info/METADATA
let45fc_paginator-0.1.dist-info/WHEEL
let45fc_paginator-0.1.dist-info/top_level.txt
let45fc_paginator-0.1.dist-info/RECORD
