Metadata-Version: 2.1
Name: let45fc-paginator
Version: 0.1
Summary: paginator
Home-page: https://github.com/HolidayMan/holidayman-paginator
Author: let45fc
Author-email: let45fc@gmail.com
License: UNKNOWN
Platform: UNKNOWN
Classifier: Programming Language :: Python :: 3
Classifier: License :: OSI Approved :: MIT License
Classifier: Operating System :: OS Independent
Requires-Python: >=3.6
